s3contents/__about__.py
s3contents/__init__.py
s3contents/chunks.py
s3contents/genericfs.py
s3contents/genericmanager.py
s3contents/ipycompat.py
s3contents/s3_fs.py
s3contents/s3manager.py
s3contents/gcs/__init__.py
s3contents/gcs/gcs_fs.py
s3contents/gcs/gcsmanager.py
s3contents/tests/__init__.py
s3contents/tests/hooks.py
s3contents/tests/test_pkg.py
s3contents/tests/test_s3manager.py
s3contents/tests/test_s3manager_chunked.py
s3contents/tests/test_s3manager_with_prefix.py
s3contents/tests/utils.py
s3contents/tests/gcs/test_gcsmanager.py
s3contents/tests/gcs/test_gcsmanager_chunked.py
s3contents/tests/gcs/test_gcsmanager_with_prefix.py
s3contents-0.11.2.dist-info/METADATA
s3contents-0.11.2.dist-info/WHEEL
s3contents-0.11.2.dist-info/licenses/LICENSE.txt
s3contents-0.11.2.dist-info/RECORD
