Metadata-Version: 2.1
Name: s3contents
Version: 0.11.2
Summary: S3 Contents Manager for Jupyter
Project-URL: Documentation, https://github.com/danielfrg/s3contents#readme
Project-URL: Issues, https://github.com/danielfrg/s3contents/issues
Project-URL: Source, https://github.com/danielfrg/s3contents
Author-email: Daniel Rodriguez <daniel@danielfrg.com>
License-Expression: Apache-2.0
License-File: LICENSE.txt
Keywords: aws,gcs,google cloud storage,jupyter,jupyterlab,minio,notebooks,s3
Classifier: Development Status :: 5 - Production/Stable
Classifier: Programming Language :: Python
Classifier: Programming Language :: Python :: 3.8
Classifier: Programming Language :: Python :: 3.9
Classifier: Programming Language :: Python :: 3.10
Classifier: Programming Language :: Python :: 3.11
Classifier: Programming Language :: Python :: Implementation :: CPython
Classifier: Programming Language :: Python :: Implementation :: PyPy
Requires-Python: >=3.7
Requires-Dist: aiobotocore[boto3]>=1.4.0
Requires-Dist: gcsfs>=2021.11.0
Requires-Dist: nbconvert<8.0,>=6.0
Requires-Dist: s3fs>=2021.11.0
Provides-Extra: test
Requires-Dist: coverage[toml]; extra == 'test'
Requires-Dist: nose; extra == 'test'
Requires-Dist: pytest; extra == 'test'
Requires-Dist: pytest-cov; extra == 'test'
